hubspaceng/__init__.py
hubspaceng/account.py
hubspaceng/api.py
hubspaceng/const.py
hubspaceng/errors.py
hubspaceng/request.py
hubspaceng/util.py
hubspaceng/models/__init__.py
hubspaceng/models/devices/__init__.py
hubspaceng/models/devices/base.py
hubspaceng/models/devices/combo.py
hubspaceng/models/devices/fan.py
hubspaceng/models/devices/lock.py
hubspaceng/models/devices/plug.py
hubspaceng/models/devices/lights/__init__.py
hubspaceng/models/devices/lights/base.py
hubspaceng/models/devices/lights/rgb.py
hubspaceng/models/devices/lights/tunable.py
hubspaceng/models/functions/__init__.py
hubspaceng/models/functions/base.py
hubspaceng/models/functions/category.py
hubspaceng/models/functions/color.py
hubspaceng/models/functions/range.py
hubspaceng/models/places/__init__.py
hubspaceng/models/places/home.py
hubspaceng/models/places/place.py
hubspaceng/models/places/room.py
hubspaceng/tools/__init__.py
hubspaceng/tools/report.py
hubspaceng/tools/survey.py
hubspaceng/tools/test_connect.py
hubspace_ng-0.0.4.dist-info/LICENSE
hubspace_ng-0.0.4.dist-info/METADATA
hubspace_ng-0.0.4.dist-info/WHEEL
hubspace_ng-0.0.4.dist-info/top_level.txt
hubspace_ng-0.0.4.dist-info/RECORD
