Metadata-Version: 2.1
Name: hubspace-ng
Version: 0.0.4
Summary: A python package to interface with the Afero Hubspace service for smart home devices
Author-email: Shawn McNaughton <shawngmc@gmail.com>
License: MIT License
Project-URL: Homepage, https://github.com/shawngmc/hubspace-ng
Project-URL: Bug Tracker, https://github.com/shawngmc/hubspace-ng/issues
Requires-Python: >=3.9
License-File: LICENSE
Requires-Dist: aiohttp >=3.8.3
Requires-Dist: pkce >=1.0.3
